ws1in44lcd/LCD.py
ws1in44lcd/__init__.py
ws1in44lcd/config.py
ws1in44lcd/demo.py
ws1in44lcd/keys.py
ws1in44lcd-0.0.1.dist-info/METADATA
ws1in44lcd-0.0.1.dist-info/WHEEL
ws1in44lcd-0.0.1.dist-info/top_level.txt
ws1in44lcd-0.0.1.dist-info/RECORD
