Metadata-Version: 2.1
Name: ws1in44lcd
Version: 0.0.1
Summary: A python library for the WaveShare 1.44in LCD HAT
Home-page: https://github.com/tsbarnes/ws1in44lcd
Author: Thea Barnes
Author-email: thea@tsbarnes.com
License: UNKNOWN
Project-URL: Bug Tracker, https://github.com/tsbarnes/ws1in44lcd/issues
Platform: UNKNOWN
Classifier: Programming Language :: Python :: 3
Classifier: License :: OSI Approved :: MIT License
Classifier: Operating System :: POSIX :: Linux
Requires-Python: >=3.6
